odoo/addons/mrp_subcontracting_purchase_link/README.rst
odoo/addons/mrp_subcontracting_purchase_link/__init__.py
odoo/addons/mrp_subcontracting_purchase_link/__manifest__.py
odoo/addons/mrp_subcontracting_purchase_link/i18n/it.po
odoo/addons/mrp_subcontracting_purchase_link/i18n/ja.po
odoo/addons/mrp_subcontracting_purchase_link/i18n/mrp_subcontracting_purchase_link.pot
odoo/addons/mrp_subcontracting_purchase_link/i18n/pt_BR.po
odoo/addons/mrp_subcontracting_purchase_link/models/__init__.py
odoo/addons/mrp_subcontracting_purchase_link/models/mrp_production.py
odoo/addons/mrp_subcontracting_purchase_link/models/purchase_order.py
odoo/addons/mrp_subcontracting_purchase_link/models/stock_picking.py
odoo/addons/mrp_subcontracting_purchase_link/readme/CONTRIBUTORS.rst
odoo/addons/mrp_subcontracting_purchase_link/readme/DESCRIPTION.rst
odoo/addons/mrp_subcontracting_purchase_link/static/description/icon.png
odoo/addons/mrp_subcontracting_purchase_link/static/description/index.html
odoo/addons/mrp_subcontracting_purchase_link/tests/__init__.py
odoo/addons/mrp_subcontracting_purchase_link/tests/test_mrp_subcontracting_purchase_link.py
odoo/addons/mrp_subcontracting_purchase_link/views/mrp_production_views.xml
odoo/addons/mrp_subcontracting_purchase_link/views/purchase_order_views.xml
odoo12_addon_mrp_subcontracting_purchase_link-12.0.1.0.0.99.dev8.dist-info/METADATA
odoo12_addon_mrp_subcontracting_purchase_link-12.0.1.0.0.99.dev8.dist-info/WHEEL
odoo12_addon_mrp_subcontracting_purchase_link-12.0.1.0.0.99.dev8.dist-info/top_level.txt
odoo12_addon_mrp_subcontracting_purchase_link-12.0.1.0.0.99.dev8.dist-info/RECORD
