Metadata-Version: 2.1
Name: odoo12-addon-mrp-subcontracting-purchase-link
Version: 12.0.1.0.0.99.dev8
Summary: Link Purchase Order to Subcontract Productions
Home-page: https://github.com/OCA/manufacture
Author: Quartile Limited, Odoo Community Association (OCA)
Author-email: support@odoo-community.org
License: LGPL-3
Platform: UNKNOWN
Classifier: Programming Language :: Python
Classifier: Framework :: Odoo
Classifier: Framework :: Odoo :: 12.0
Classifier: License :: OSI Approved :: GNU Lesser General Public License v3 (LGPLv3)
Requires-Python: >=3.5
Requires-Dist: odoo12-addon-mrp-subcontracting
Requires-Dist: odoo <12.1dev,>=12.0a
